tb_nightly-2.21.0a20251022.dist-info/licenses/LICENSE
tensorboard/__init__.py
tensorboard/assets.py
tensorboard/auth.py
tensorboard/context.py
tensorboard/data_compat.py
tensorboard/dataclass_compat.py
tensorboard/default.py
tensorboard/errors.py
tensorboard/lazy.py
tensorboard/main.py
tensorboard/main_lib.py
tensorboard/manager.py
tensorboard/notebook.py
tensorboard/plugin_util.py
tensorboard/program.py
tensorboard/version.py
tensorboard/webfiles.zip
tensorboard/_vendor/__init__.py
tensorboard/_vendor/bleach/__init__.py
tensorboard/_vendor/bleach/callbacks.py
tensorboard/_vendor/bleach/html5lib_shim.py
tensorboard/_vendor/bleach/linkifier.py
tensorboard/_vendor/bleach/parse_shim.py
tensorboard/_vendor/bleach/sanitizer.py
tensorboard/_vendor/bleach/six_shim.py
tensorboard/_vendor/bleach/_vendor/__init__.py
tensorboard/_vendor/bleach/_vendor/parse.py
tensorboard/_vendor/bleach/_vendor/html5lib/__init__.py
tensorboard/_vendor/bleach/_vendor/html5lib/_ihatexml.py
tensorboard/_vendor/bleach/_vendor/html5lib/_inputstream.py
tensorboard/_vendor/bleach/_vendor/html5lib/_tokenizer.py
tensorboard/_vendor/bleach/_vendor/html5lib/_utils.py
tensorboard/_vendor/bleach/_vendor/html5lib/constants.py
tensorboard/_vendor/bleach/_vendor/html5lib/html5parser.py
tensorboard/_vendor/bleach/_vendor/html5lib/serializer.py
tensorboard/_vendor/bleach/_vendor/html5lib/_trie/__init__.py
tensorboard/_vendor/bleach/_vendor/html5lib/_trie/_base.py
tensorboard/_vendor/bleach/_vendor/html5lib/_trie/py.py
tensorboard/_vendor/bleach/_vendor/html5lib/filters/__init__.py
tensorboard/_vendor/bleach/_vendor/html5lib/filters/alphabeticalattributes.py
tensorboard/_vendor/bleach/_vendor/html5lib/filters/base.py
tensorboard/_vendor/bleach/_vendor/html5lib/filters/inject_meta_charset.py
tensorboard/_vendor/bleach/_vendor/html5lib/filters/lint.py
tensorboard/_vendor/bleach/_vendor/html5lib/filters/optionaltags.py
tensorboard/_vendor/bleach/_vendor/html5lib/filters/sanitizer.py
tensorboard/_vendor/bleach/_vendor/html5lib/filters/whitespace.py
tb_nightly-2.21.0a20251022.dist-info/METADATA
tb_nightly-2.21.0a20251022.dist-info/WHEEL
tb_nightly-2.21.0a20251022.dist-info/entry_points.txt
tb_nightly-2.21.0a20251022.dist-info/top_level.txt
tb_nightly-2.21.0a20251022.dist-info/RECORD
